yolo4tab/__init__.py
yolo4tab/const.py
yolo4tab/table_extraction.py
yolo4tab/table_detection/__init__.py
yolo4tab/table_detection/table_detection.py
yolo4tab/table_reconstruction/__init__.py
yolo4tab/table_reconstruction/table_reconstruction.py
yolo4tab/table_structure_recognition/__init__.py
yolo4tab/table_structure_recognition/table_structure_recognition.py
yolo4tab/text_extraction/__init__.py
yolo4tab/text_extraction/text_extraction.py
yolo4tab/utils/__init__.py
yolo4tab/utils/common.py
yolo4tab/utils/general.py
yolo4tab/utils/warp.py
yolo4tab-0.2.3.dist-info/LICENSE
yolo4tab-0.2.3.dist-info/METADATA
yolo4tab-0.2.3.dist-info/WHEEL
yolo4tab-0.2.3.dist-info/top_level.txt
yolo4tab-0.2.3.dist-info/RECORD
