Metadata-Version: 2.1
Name: yolo4tab
Version: 0.2.3
Summary: An End-to-End table extraction system for printed documents based on YOLOv9.
Author-email: vm7608 <vanmanh76o8@gmail.com>
License: MIT License
Project-URL: Homepage, https://vm7608.github.io/
Project-URL: Documentation, https://vm7608.github.io/
Keywords: Table Extraction,Table Detection,Table Structure Recognition,Text Extraction,YOLO
Classifier: Intended Audience :: Developers
Classifier: Programming Language :: Python :: 3
Classifier: License :: OSI Approved :: MIT License
Classifier: Operating System :: OS Independent
Requires-Python: >=3.8
License-File: LICENSE
Requires-Dist: dill
Requires-Dist: ultralytics
Requires-Dist: easyocr
Requires-Dist: StrEnum
Requires-Dist: gdown ==5.1.0
Requires-Dist: PyMuPDF
